{
  "resourceType": "CodeSystem",
  "status": "draft",
  "content": "complete",
  "name": "MII_CS_Kardio_Ausschlusskriterium_ACRIBiS_Scores",
  "id": "mii-cs-kardio-ausschlusskriterium-acribis-scores",
  "title": "MII CS Kardio Ausschlusskriterium ACRIBiS Scores",
  "description": "Ausschlusskriterien für ACRIBiS Scores",
  "url": "https://www.medizininformatik-initiative.de/fhir/ext/modul-kardio/CodeSystem/mii-cs-kardio-ausschlusskriterium-acribis-scores",
  "concept": [
    {
      "code": "hv",
      "display": "Ausschlusskriterium unbehandeltes, höhergradiges Vitium"
    }
  ],
  "version": "2025.0.0",
  "publisher": "Medizininformatik Initiative",
  "contact": [
    {
      "telecom": [
        {
          "system": "url",
          "value": "https://www.medizininformatik-initiative.de"
        }
      ]
    }
  ],
  "experimental": true,
  "date": "2025-05-21",
  "caseSensitive": true,
  "valueSet": "https://www.medizininformatik-initiative.de/fhir/ext/modul-kardio/ValueSet/mii-vs-kardio-ausschlusskriterium-acribis-scores",
  "count": 1
}
