{
  "resourceType": "StructureDefinition",
  "id": "region-extension",
  "url": "https://www.medizininformatik-initiative.de/fhir/ext/modul-kardio/StructureDefinition/region-extension",
  "name": "RegionExtension",
  "title": "Region (Wohnort/Land) nach best. HF-Risk-Score",
  "status": "draft",
  "description": "Angabe einer Region mit einem ValueSet definiert in ACRIBiS-Datensatz.",
  "fhirVersion": "4.0.1",
  "kind": "complex-type",
  "abstract": false,
  "context": [
    {
      "type": "element",
      "expression": "Element"
    }
  ],
  "type": "Extension",
  "baseDefinition": "http://hl7.org/fhir/StructureDefinition/Extension",
  "derivation": "constraint",
  "differential": {
    "element": [
      {
        "id": "Extension",
        "path": "Extension",
        "short": "Region (Wohnort/Land) nach best. HF-Risk-Score",
        "definition": "Angabe einer Region mit einem ValueSet definiert in ACRIBiS-Datensatz."
      },
      {
        "id": "Extension.extension",
        "path": "Extension.extension",
        "max": "0"
      },
      {
        "id": "Extension.url",
        "path": "Extension.url",
        "fixedUri": "https://www.medizininformatik-initiative.de/fhir/ext/modul-kardio/StructureDefinition/region-extension"
      },
      {
        "id": "Extension.value[x]",
        "path": "Extension.value[x]",
        "slicing": {
          "discriminator": [
            {
              "type": "type",
              "path": "$this"
            }
          ],
          "ordered": false,
          "rules": "open"
        },
        "min": 1
      },
      {
        "id": "Extension.value[x]:valueString",
        "path": "Extension.value[x]",
        "sliceName": "valueString",
        "min": 1,
        "max": "1",
        "type": [
          {
            "code": "string"
          }
        ]
      }
    ]
  }
}
